switchsources/__init__.py
switchsources/app.py
switchsources/config.py
switchsources/switcher.py
switchsources-0.2.2.dist-info/LICENSE
switchsources-0.2.2.dist-info/METADATA
switchsources-0.2.2.dist-info/WHEEL
switchsources-0.2.2.dist-info/entry_points.txt
switchsources-0.2.2.dist-info/RECORD
