Metadata-Version: 2.1
Name: switchsources
Version: 0.2.2
Summary: A tool to switch sources
Author: Dragonchu
Requires-Python: >=3.10,<4.0
Classifier: Programming Language :: Python :: 3
Classifier: Programming Language :: Python :: 3.10
Classifier: Programming Language :: Python :: 3.11
Classifier: Programming Language :: Python :: 3.12
Requires-Dist: inquirer (>=3.2.4,<4.0.0)
Requires-Dist: platformdirs (>=4.2.2,<5.0.0)
Requires-Dist: typer (>=0.12.3,<0.13.0)
